check_talend_job/__init__.py
check_talend_job/check_talend_job.py
check_talend_job/config.py
check_talend_job/tests/test_check_talend_job.py
check_task_log/__init__.py
check_task_log/check_task_log.py
check_task_log/config.ini
check_task_log/tests/test_check_task_log.py
check_task_log-1.0.dev0.dist-info/DESCRIPTION.rst
check_task_log-1.0.dev0.dist-info/METADATA
check_task_log-1.0.dev0.dist-info/RECORD
check_task_log-1.0.dev0.dist-info/WHEEL
check_task_log-1.0.dev0.dist-info/entry_points.txt
check_task_log-1.0.dev0.dist-info/metadata.json
check_task_log-1.0.dev0.dist-info/top_level.txt
