Metadata-Version: 2.0
Name: check-task-log
Version: 1.0.dev0
Summary: A nagios-like plugin to check if task jobs executed successfully
Home-page: https://github.com/paulla/check_task_log
Author: Elio Maisonneuve
Author-email: maisonneuv@eisti.eu
License: BSD
Keywords: nagios
Platform: any
Classifier: Programming Language :: Python
Classifier: License :: OSI Approved :: BSD License
Requires-Dist: setuptools
